has9_pkg1/__init__.py
has9_pkg1/common.py
has9_pkg1/has9_pkg1.py
has9_pkg1-0.0.1.dist-info/licenses/LICENSE
has9_pkg1-0.0.1.dist-info/METADATA
has9_pkg1-0.0.1.dist-info/WHEEL
has9_pkg1-0.0.1.dist-info/entry_points.txt
has9_pkg1-0.0.1.dist-info/top_level.txt
has9_pkg1-0.0.1.dist-info/RECORD
