Metadata-Version: 2.4
Name: Has9_pkg1
Version: 0.0.1
Summary: Learning how to publish a python package in pypi
Author-email: Hasnein Tareque <hasnein.tareque@dpird.wa.gov.au>
License: MIT License
Project-URL: Homepage, https://github.com/HasTarC0d3/Has9_pkg1
Keywords: Has9_pkg1
Classifier: Intended Audience :: Developers
Classifier: License :: OSI Approved :: MIT License
Classifier: Natural Language :: English
Classifier: Programming Language :: Python :: 3.8
Classifier: Programming Language :: Python :: 3.9
Classifier: Programming Language :: Python :: 3.10
Classifier: Programming Language :: Python :: 3.11
Classifier: Programming Language :: Python :: 3.12
Requires-Python: >=3.8
License-File: LICENSE
Requires-Dist: numpy
Provides-Extra: all
Requires-Dist: Has9_pkg1[extra]; extra == "all"
Provides-Extra: extra
Requires-Dist: pandas; extra == "extra"
Dynamic: license-file
